pyterrier_doc2query/__init__.py
pyterrier_doc2query/artefact.py
pyterrier_doc2query/filtering.py
pyterrier_doc2query/stores.py
pyterrier_doc2query/pt_docs/index.rst
pyterrier_doc2query-0.2.0.dist-info/licenses/LICENSE
pyterrier_doc2query-0.2.0.dist-info/METADATA
pyterrier_doc2query-0.2.0.dist-info/WHEEL
pyterrier_doc2query-0.2.0.dist-info/top_level.txt
pyterrier_doc2query-0.2.0.dist-info/RECORD
