Metadata-Version: 2.4
Name: pyterrier-doc2query
Version: 0.2.0
Summary: PyTerrier components for doc2query
Author-email: Craig Macdonald <craig.macdonald@glasgow.ac.uk>, Sean MacAvaney <sean.macavaney@glasgow.ac.uk>
Maintainer-email: Craig Macdonald <craig.macdonald@glasgow.ac.uk>, Sean MacAvaney <sean.macavaney@glasgow.ac.uk>
Project-URL: Repository, https://github.com/terrierteam/pyterrier_doc2query
Project-URL: Bug Tracker, https://github.com/terrierteam/pyterrier_doc2query/issues
Classifier: Programming Language :: Python
Classifier: Operating System :: OS Independent
Classifier: Topic :: Text Processing
Classifier: Topic :: Text Processing :: Indexing
Classifier: License :: OSI Approved :: MIT License
Requires-Python: >=3.6
License-File: LICENSE
Requires-Dist: python-terrier>=0.5.0
Requires-Dist: pandas
Requires-Dist: transformers
Requires-Dist: torch
Requires-Dist: sentencepiece
Requires-Dist: GitPython
Requires-Dist: npids
Requires-Dist: pyterrier-alpha
Dynamic: license-file
